setup.py
pyhdl/__init__.py
pyhdl/gate.py
pyhdl/primitives.py
pyhdl/simulator.py
pyhdl/utils.py
pyhdl/wire.py
pyhdl.egg-info/PKG-INFO
pyhdl.egg-info/SOURCES.txt
pyhdl.egg-info/dependency_links.txt
pyhdl.egg-info/not-zip-safe
pyhdl.egg-info/requires.txt
pyhdl.egg-info/top_level.txt