Metadata-Version: 1.1
Name: pyhdl
Version: 0.3.0
Summary: A simpe HDL for learning hardware design.
Home-page: https://github.com/SdNssr/pyhdl
Author: Saad Nasser
Author-email: SdNssr@users.noreply.github.com
License: MIT
Keywords: hdl hardware design simple
Platform: UNKNOWN
Classifier: Development Status :: 3 - Alpha
Classifier: Operating System :: OS Independent
Classifier: Programming Language :: Python
Classifier: Programming Language :: Python :: 2
Classifier: Programming Language :: Python :: 2.7
Classifier: Programming Language :: Python :: 3
Classifier: Programming Language :: Python :: 3.3
Classifier: Programming Language :: Python :: 3.4
Classifier: Programming Language :: Python :: 3.5
Classifier: License :: OSI Approved :: MIT License
Classifier: Topic :: Software Development :: Interpreters
